.fig.yaml
LICENSE
README.md
setup.cfg
setup.py
omnibelt/__init__.py
omnibelt/basic_containers.py
omnibelt/containers.py
omnibelt/crafts.py
omnibelt/environment.py
omnibelt/errors.py
omnibelt/exporting.py
omnibelt/exporting_common.py
omnibelt/farming.py
omnibelt/filesystem.py
omnibelt/flow.py
omnibelt/hashing.py
omnibelt/loggers.py
omnibelt/logic.py
omnibelt/math.py
omnibelt/nodes.py
omnibelt/operators.py
omnibelt/ordered_set.py
omnibelt/packing.py
omnibelt/patterns.py
omnibelt/propagators.py
omnibelt/pure_packing.py
omnibelt/registries.py
omnibelt/structured.py
omnibelt/timing.py
omnibelt/transactions.py
omnibelt/tricks.py
omnibelt/typelike.py
omnibelt/utils.py
omnibelt/viz.py
omnibelt/wrappers.py
omnibelt.egg-info/PKG-INFO
omnibelt.egg-info/SOURCES.txt
omnibelt.egg-info/dependency_links.txt
omnibelt.egg-info/requires.txt
omnibelt.egg-info/top_level.txt
omnibelt/complex/__init__.py
omnibelt/complex/choices.py
omnibelt/jester/__init__.py
omnibelt/jester/abstract.py
omnibelt/jester/convenience.py
omnibelt/jester/imports.py
omnibelt/jester/paths.py
omnibelt/jester/progress_bar.py
omnibelt/jester/simple.py
omnibelt/jester/unit_test.py
tests/test_basics.py
tests/test_packing.py
tests/test_transactions.py
tests/test_wrappers.py