Metadata-Version: 2.1
Name: omnibelt
Version: 0.8.9
Summary: "Omni-belt: A Tool-belt containing pure python utilities for downstream projects"
Home-page: https://github.com/felixludos/omni-belt
Author: Felix Leeb
Author-email: felixludos.info@gmail.com
License: MIT
Classifier: Programming Language :: Python :: 3.8
License-File: LICENSE
Requires-Dist: pyyaml>=6.0.1
Requires-Dist: dill>=0.3.7
Requires-Dist: wrapt>=1.15.0
Requires-Dist: indexed==1.3.0
Requires-Dist: tqdm>=4.65.0
Requires-Dist: tabulate>=0.9.0
Provides-Extra: test
Requires-Dist: pytest; extra == "test"
